odoo/addons/connector_elasticsearch/README.rst
odoo/addons/connector_elasticsearch/__init__.py
odoo/addons/connector_elasticsearch/__manifest__.py
odoo/addons/connector_elasticsearch/components/__init__.py
odoo/addons/connector_elasticsearch/components/adapter.py
odoo/addons/connector_elasticsearch/components/core.py
odoo/addons/connector_elasticsearch/demo/backend_demo.xml
odoo/addons/connector_elasticsearch/i18n/connector_elasticsearch.pot
odoo/addons/connector_elasticsearch/models/__init__.py
odoo/addons/connector_elasticsearch/models/se_backend_elasticsearch.py
odoo/addons/connector_elasticsearch/models/se_index.py
odoo/addons/connector_elasticsearch/models/se_index_config.py
odoo/addons/connector_elasticsearch/readme/CONTRIBUTORS.rst
odoo/addons/connector_elasticsearch/readme/DESCRIPTION.rst
odoo/addons/connector_elasticsearch/readme/HISTORY.rst
odoo/addons/connector_elasticsearch/security/se_backend_elasticsearch.xml
odoo/addons/connector_elasticsearch/security/se_index_config.xml
odoo/addons/connector_elasticsearch/static/description/icon.png
odoo/addons/connector_elasticsearch/static/description/index.html
odoo/addons/connector_elasticsearch/tests/__init__.py
odoo/addons/connector_elasticsearch/tests/test_connector_elasticsearch.py
odoo/addons/connector_elasticsearch/tests/cassettes/TestConnectorElasticsearch.test_index_adapter.yaml
odoo/addons/connector_elasticsearch/tests/cassettes/TestConnectorElasticsearch.test_index_adapter_delete.yaml
odoo/addons/connector_elasticsearch/tests/cassettes/TestConnectorElasticsearch.test_index_adapter_delete_nonexisting_documents.yaml
odoo/addons/connector_elasticsearch/tests/cassettes/TestConnectorElasticsearch.test_index_adapter_iter.yaml
odoo/addons/connector_elasticsearch/tests/cassettes/TestConnectorElasticsearch.test_index_adapter_no_objectID.yaml
odoo/addons/connector_elasticsearch/views/se_backend_elasticsearch.xml
odoo/addons/connector_elasticsearch/views/se_index_config.xml
odoo12_addon_connector_elasticsearch-12.0.1.1.1.dist-info/METADATA
odoo12_addon_connector_elasticsearch-12.0.1.1.1.dist-info/WHEEL
odoo12_addon_connector_elasticsearch-12.0.1.1.1.dist-info/top_level.txt
odoo12_addon_connector_elasticsearch-12.0.1.1.1.dist-info/RECORD
