Metadata-Version: 2.1
Name: odoo12-addon-connector-elasticsearch
Version: 12.0.1.1.1
Summary: Connector For Elasticsearch Search Engine
Home-page: https://github.com/OCA/search-engine
Author: ACSONE SA/NV, Odoo Community Association (OCA)
Author-email: support@odoo-community.org
License: AGPL-3
Platform: UNKNOWN
Classifier: Programming Language :: Python
Classifier: Framework :: Odoo
Classifier: License :: OSI Approved :: GNU Affero General Public License v3
Requires-Python: >=3.5
Requires-Dist: elasticsearch (<8.0.0,>=7.0.0)
Requires-Dist: odoo12-addon-base-jsonify
Requires-Dist: odoo12-addon-component
Requires-Dist: odoo12-addon-connector
Requires-Dist: odoo12-addon-connector-search-engine
Requires-Dist: odoo (<12.1dev,>=12.0a)
Requires-Dist: requests
